adafruit_l3gd20.py
adafruit_circuitpython_l3gd20-2.3.25.dist-info/licenses/LICENSE
adafruit_circuitpython_l3gd20-2.3.25.dist-info/METADATA
adafruit_circuitpython_l3gd20-2.3.25.dist-info/WHEEL
adafruit_circuitpython_l3gd20-2.3.25.dist-info/top_level.txt
adafruit_circuitpython_l3gd20-2.3.25.dist-info/RECORD
