Metadata-Version: 2.4
Name: adafruit-circuitpython-l3gd20
Version: 2.3.25
Summary: CircuitPython library for L3GD20 9-DOF absolute orientation IMU fusion breakout.
Author-email: Adafruit Industries <circuitpython@adafruit.com>
License: MIT
Project-URL: Homepage, https://github.com/adafruit/Adafruit_CircuitPython_L3GD20
Keywords: adafruit,9dof,9-dof,absolute,orientation,IMU,fusion,breakout,hardwarel3gd20,micropython,circuitpython
Classifier: Intended Audience :: Developers
Classifier: Topic :: Software Development :: Libraries
Classifier: Topic :: Software Development :: Embedded Systems
Classifier: Topic :: System :: Hardware
Classifier: License :: OSI Approved :: MIT License
Classifier: Programming Language :: Python :: 3
License-File: LICENSE
Requires-Dist: Adafruit-Blinka
Requires-Dist: adafruit-circuitpython-register
Requires-Dist: adafruit-circuitpython-typing
Provides-Extra: optional
Dynamic: license-file
